[{"character":" ","windows1252":"%20","utf8":"%20"},{"character":"!","windows1252":"%21","utf8":"%21"},{"character":"\"","windows1252":"%22","utf8":"%22"},{"character":"#","windows1252":"%23","utf8":"%23"},{"character":"$","windows1252":"%24","utf8":"%24"},{"character":"%","windows1252":"%25","utf8":"%25"},{"character":"&amp;","windows1252":"%26","utf8":"%26"},{"character":"'","windows1252":"%27","utf8":"%27"},{"character":"(","windows1252":"%28","utf8":"%28"},{"character":")","windows1252":"%29","utf8":"%29"},{"character":"*","windows1252":"%2A","utf8":"%2A"},{"character":"+","windows1252":"%2B","utf8":"%2B"},{"character":",","windows1252":"%2C","utf8":"%2C"},{"character":"-","windows1252":"%2D","utf8":"%2D"},{"character":".","windows1252":"%2E","utf8":"%2E"},{"character":"/","windows1252":"%2F","utf8":"%2F"},{"character":"0","windows1252":"%30","utf8":"%30"},{"character":"1","windows1252":"%31","utf8":"%31"},{"character":"2","windows1252":"%32","utf8":"%32"},{"character":"3","windows1252":"%33","utf8":"%33"},{"character":"4","windows1252":"%34","utf8":"%34"},{"character":"5","windows1252":"%35","utf8":"%35"},{"character":"6","windows1252":"%36","utf8":"%36"},{"character":"7","windows1252":"%37","utf8":"%37"},{"character":"8","windows1252":"%38","utf8":"%38"},{"character":"9","windows1252":"%39","utf8":"%39"},{"character":":","windows1252":"%3A","utf8":"%3A"},{"character":";","windows1252":"%3B","utf8":"%3B"},{"character":"&lt;","windows1252":"%3C","utf8":"%3C"},{"character":"=","windows1252":"%3D","utf8":"%3D"},{"character":"&gt;","windows1252":"%3E","utf8":"%3E"},{"character":"?","windows1252":"%3F","utf8":"%3F"},{"character":"@","windows1252":"%40","utf8":"%40"},{"character":"A","windows1252":"%41","utf8":"%41"},{"character":"B","windows1252":"%42","utf8":"%42"},{"character":"C","windows1252":"%43","utf8":"%43"},{"character":"D","windows1252":"%44","utf8":"%44"},{"character":"E","windows1252":"%45","utf8":"%45"},{"character":"F","windows1252":"%46","utf8":"%46"},{"character":"G","windows1252":"%47","utf8":"%47"},{"character":"H","windows1252":"%48","utf8":"%48"},{"character":"I","windows1252":"%49","utf8":"%49"},{"character":"J","windows1252":"%4A","utf8":"%4A"},{"character":"K","windows1252":"%4B","utf8":"%4B"},{"character":"L","windows1252":"%4C","utf8":"%4C"},{"character":"M","windows1252":"%4D","utf8":"%4D"},{"character":"N","windows1252":"%4E","utf8":"%4E"},{"character":"O","windows1252":"%4F","utf8":"%4F"},{"character":"P","windows1252":"%50","utf8":"%50"},{"character":"Q","windows1252":"%51","utf8":"%51"},{"character":"R","windows1252":"%52","utf8":"%52"},{"character":"S","windows1252":"%53","utf8":"%53"},{"character":"T","windows1252":"%54","utf8":"%54"},{"character":"U","windows1252":"%55","utf8":"%55"},{"character":"V","windows1252":"%56","utf8":"%56"},{"character":"W","windows1252":"%57","utf8":"%57"},{"character":"X","windows1252":"%58","utf8":"%58"},{"character":"Y","windows1252":"%59","utf8":"%59"},{"character":"Z","windows1252":"%5A","utf8":"%5A"},{"character":"[","windows1252":"%5B","utf8":"%5B"},{"character":"\\","windows1252":"%5C","utf8":"%5C"},{"character":"]","windows1252":"%5D","utf8":"%5D"},{"character":"^","windows1252":"%5E","utf8":"%5E"},{"character":"_","windows1252":"%5F","utf8":"%5F"},{"character":"`","windows1252":"%60","utf8":"%60"},{"character":"a","windows1252":"%61","utf8":"%61"},{"character":"b","windows1252":"%62","utf8":"%62"},{"character":"c","windows1252":"%63","utf8":"%63"},{"character":"d","windows1252":"%64","utf8":"%64"},{"character":"e","windows1252":"%65","utf8":"%65"},{"character":"f","windows1252":"%66","utf8":"%66"},{"character":"g","windows1252":"%67","utf8":"%67"},{"character":"h","windows1252":"%68","utf8":"%68"},{"character":"i","windows1252":"%69","utf8":"%69"},{"character":"j","windows1252":"%6A","utf8":"%6A"},{"character":"k","windows1252":"%6B","utf8":"%6B"},{"character":"l","windows1252":"%6C","utf8":"%6C"},{"character":"m","windows1252":"%6D","utf8":"%6D"},{"character":"n","windows1252":"%6E","utf8":"%6E"},{"character":"o","windows1252":"%6F","utf8":"%6F"},{"character":"p","windows1252":"%70","utf8":"%70"},{"character":"q","windows1252":"%71","utf8":"%71"},{"character":"r","windows1252":"%72","utf8":"%72"},{"character":"s","windows1252":"%73","utf8":"%73"},{"character":"t","windows1252":"%74","utf8":"%74"},{"character":"u","windows1252":"%75","utf8":"%75"},{"character":"v","windows1252":"%76","utf8":"%76"},{"character":"w","windows1252":"%77","utf8":"%77"},{"character":"x","windows1252":"%78","utf8":"%78"},{"character":"y","windows1252":"%79","utf8":"%79"},{"character":"z","windows1252":"%7A","utf8":"%7A"},{"character":"{","windows1252":"%7B","utf8":"%7B"},{"character":"|","windows1252":"%7C","utf8":"%7C"},{"character":"}","windows1252":"%7D","utf8":"%7D"},{"character":"~","windows1252":"%7E","utf8":"%7E"},{"character":"&nbsp;","windows1252":"%7F","utf8":"%7F"},{"character":"\n","windows1252":"%80","utf8":"%E2%82%AC"},{"character":"","windows1252":"%81","utf8":"%81"},{"character":"‚","windows1252":"%82","utf8":"%E2%80%9A"},{"character":"ƒ","windows1252":"%83","utf8":"%C6%92"},{"character":"„","windows1252":"%84","utf8":"%E2%80%9E"},{"character":"…","windows1252":"%85","utf8":"%E2%80%A6"},{"character":"†","windows1252":"%86","utf8":"%E2%80%A0"},{"character":"‡","windows1252":"%87","utf8":"%E2%80%A1"},{"character":"ˆ","windows1252":"%88","utf8":"%CB%86"},{"character":"‰","windows1252":"%89","utf8":"%E2%80%B0"},{"character":"Š","windows1252":"%8A","utf8":"%C5%A0"},{"character":"‹","windows1252":"%8B","utf8":"%E2%80%B9"},{"character":"Œ","windows1252":"%8C","utf8":"%C5%92"},{"character":"","windows1252":"%8D","utf8":"%C5%8D"},{"character":"Ž","windows1252":"%8E","utf8":"%C5%BD"},{"character":"","windows1252":"%8F","utf8":"%8F"},{"character":"","windows1252":"%90","utf8":"%C2%90"},{"character":"‘","windows1252":"%91","utf8":"%E2%80%98"},{"character":"’","windows1252":"%92","utf8":"%E2%80%99"},{"character":"“","windows1252":"%93","utf8":"%E2%80%9C"},{"character":"”","windows1252":"%94","utf8":"%E2%80%9D"},{"character":"•","windows1252":"%95","utf8":"%E2%80%A2"},{"character":"–","windows1252":"%96","utf8":"%E2%80%93"},{"character":"—","windows1252":"%97","utf8":"%E2%80%94"},{"character":"˜","windows1252":"%98","utf8":"%CB%9C"},{"character":"™","windows1252":"%99","utf8":"%E2%84"},{"character":"š","windows1252":"%9A","utf8":"%C5%A1"},{"character":"›","windows1252":"%9B","utf8":"%E2%80"},{"character":"œ","windows1252":"%9C","utf8":"%C5%93"},{"character":"","windows1252":"%9D","utf8":"%9D"},{"character":"ž","windows1252":"%9E","utf8":"%C5%BE"},{"character":"Ÿ","windows1252":"%9F","utf8":"%C5%B8"},{"character":"&nbsp;","windows1252":"%A0","utf8":"%C2%A0"},{"character":"¡","windows1252":"%A1","utf8":"%C2%A1"},{"character":"¢","windows1252":"%A2","utf8":"%C2%A2"},{"character":"£","windows1252":"%A3","utf8":"%C2%A3"},{"character":"¤","windows1252":"%A4","utf8":"%C2%A4"},{"character":"¥","windows1252":"%A5","utf8":"%C2%A5"},{"character":"¦","windows1252":"%A6","utf8":"%C2%A6"},{"character":"§","windows1252":"%A7","utf8":"%C2%A7"},{"character":"¨","windows1252":"%A8","utf8":"%C2%A8"},{"character":"©","windows1252":"%A9","utf8":"%C2%A9"},{"character":"ª","windows1252":"%AA","utf8":"%C2%AA"},{"character":"«","windows1252":"%AB","utf8":"%C2%AB"},{"character":"¬","windows1252":"%AC","utf8":"%C2%AC"},{"character":"­","windows1252":"%AD","utf8":"%C2%AD"},{"character":"®","windows1252":"%AE","utf8":"%C2%AE"},{"character":"¯","windows1252":"%AF","utf8":"%C2%AF"},{"character":"°","windows1252":"%B0","utf8":"%C2%B0"},{"character":"±","windows1252":"%B1","utf8":"%C2%B1"},{"character":"²","windows1252":"%B2","utf8":"%C2%B2"},{"character":"³","windows1252":"%B3","utf8":"%C2%B3"},{"character":"´","windows1252":"%B4","utf8":"%C2%B4"},{"character":"µ","windows1252":"%B5","utf8":"%C2%B5"},{"character":"¶","windows1252":"%B6","utf8":"%C2%B6"},{"character":"·","windows1252":"%B7","utf8":"%C2%B7"},{"character":"¸","windows1252":"%B8","utf8":"%C2%B8"},{"character":"¹","windows1252":"%B9","utf8":"%C2%B9"},{"character":"º","windows1252":"%BA","utf8":"%C2%BA"},{"character":"»","windows1252":"%BB","utf8":"%C2%BB"},{"character":"¼","windows1252":"%BC","utf8":"%C2%BC"},{"character":"½","windows1252":"%BD","utf8":"%C2%BD"},{"character":"¾","windows1252":"%BE","utf8":"%C2%BE"},{"character":"¿","windows1252":"%BF","utf8":"%C2%BF"},{"character":"À","windows1252":"%C0","utf8":"%C3%80"},{"character":"Á","windows1252":"%C1","utf8":"%C3%81"},{"character":"Â","windows1252":"%C2","utf8":"%C3%82"},{"character":"Ã","windows1252":"%C3","utf8":"%C3%83"},{"character":"Ä","windows1252":"%C4","utf8":"%C3%84"},{"character":"Å","windows1252":"%C5","utf8":"%C3%85"},{"character":"Æ","windows1252":"%C6","utf8":"%C3%86"},{"character":"Ç","windows1252":"%C7","utf8":"%C3%87"},{"character":"È","windows1252":"%C8","utf8":"%C3%88"},{"character":"É","windows1252":"%C9","utf8":"%C3%89"},{"character":"Ê","windows1252":"%CA","utf8":"%C3%8A"},{"character":"Ë","windows1252":"%CB","utf8":"%C3%8B"},{"character":"Ì","windows1252":"%CC","utf8":"%C3%8C"},{"character":"Í","windows1252":"%CD","utf8":"%C3%8D"},{"character":"Î","windows1252":"%CE","utf8":"%C3%8E"},{"character":"Ï","windows1252":"%CF","utf8":"%C3%8F"},{"character":"Ð","windows1252":"%D0","utf8":"%C3%90"},{"character":"Ñ","windows1252":"%D1","utf8":"%C3%91"},{"character":"Ò","windows1252":"%D2","utf8":"%C3%92"},{"character":"Ó","windows1252":"%D3","utf8":"%C3%93"},{"character":"Ô","windows1252":"%D4","utf8":"%C3%94"},{"character":"Õ","windows1252":"%D5","utf8":"%C3%95"},{"character":"Ö","windows1252":"%D6","utf8":"%C3%96"},{"character":"×","windows1252":"%D7","utf8":"%C3%97"},{"character":"Ø","windows1252":"%D8","utf8":"%C3%98"},{"character":"Ù","windows1252":"%D9","utf8":"%C3%99"},{"character":"Ú","windows1252":"%DA","utf8":"%C3%9A"},{"character":"Û","windows1252":"%DB","utf8":"%C3%9B"},{"character":"Ü","windows1252":"%DC","utf8":"%C3%9C"},{"character":"Ý","windows1252":"%DD","utf8":"%C3%9D"},{"character":"Þ","windows1252":"%DE","utf8":"%C3%9E"},{"character":"ß","windows1252":"%DF","utf8":"%C3%9F"},{"character":"à","windows1252":"%E0","utf8":"%C3%A0"},{"character":"á","windows1252":"%E1","utf8":"%C3%A1"},{"character":"â","windows1252":"%E2","utf8":"%C3%A2"},{"character":"ã","windows1252":"%E3","utf8":"%C3%A3"},{"character":"ä","windows1252":"%E4","utf8":"%C3%A4"},{"character":"å","windows1252":"%E5","utf8":"%C3%A5"},{"character":"æ","windows1252":"%E6","utf8":"%C3%A6"},{"character":"ç","windows1252":"%E7","utf8":"%C3%A7"},{"character":"è","windows1252":"%E8","utf8":"%C3%A8"},{"character":"é","windows1252":"%E9","utf8":"%C3%A9"},{"character":"ê","windows1252":"%EA","utf8":"%C3%AA"},{"character":"ë","windows1252":"%EB","utf8":"%C3%AB"},{"character":"ì","windows1252":"%EC","utf8":"%C3%AC"},{"character":"í","windows1252":"%ED","utf8":"%C3%AD"},{"character":"î","windows1252":"%EE","utf8":"%C3%AE"},{"character":"ï","windows1252":"%EF","utf8":"%C3%AF"},{"character":"ð","windows1252":"%F0","utf8":"%C3%B0"},{"character":"ñ","windows1252":"%F1","utf8":"%C3%B1"},{"character":"ò","windows1252":"%F2","utf8":"%C3%B2"},{"character":"ó","windows1252":"%F3","utf8":"%C3%B3"},{"character":"ô","windows1252":"%F4","utf8":"%C3%B4"},{"character":"õ","windows1252":"%F5","utf8":"%C3%B5"},{"character":"ö","windows1252":"%F6","utf8":"%C3%B6"},{"character":"÷","windows1252":"%F7","utf8":"%C3%B7"},{"character":"ø","windows1252":"%F8","utf8":"%C3%B8"},{"character":"ù","windows1252":"%F9","utf8":"%C3%B9"},{"character":"ú","windows1252":"%FA","utf8":"%C3%BA"},{"character":"û","windows1252":"%FB","utf8":"%C3%BB"},{"character":"ü","windows1252":"%FC","utf8":"%C3%BC"},{"character":"ý","windows1252":"%FD","utf8":"%C3%BD"},{"character":"þ","windows1252":"%FE","utf8":"%C3%BE"},{"character":"ÿ","windows1252":"%FF","utf8":"%C3%BF"},{"character":" ","utf8":"+"}]